.DS_Store
scoped_mapping/__init__.py
scoped_mapping-0.9.1.dist-info/LICENSE
scoped_mapping-0.9.1.dist-info/METADATA
scoped_mapping-0.9.1.dist-info/WHEEL
scoped_mapping-0.9.1.dist-info/top_level.txt
scoped_mapping-0.9.1.dist-info/RECORD
