Metadata-Version: 2.1
Name: scoped-mapping
Version: 0.9.1
Summary: Use orthogonal data to determine what ontologies should be used for mapping strings
Home-page: https://github.com/turbomam/scoped-mapping
Author: Mark A. Miller
Author-email: mamillerpa@yahoo.com
License: MIT
Platform: UNKNOWN
License-File: LICENSE
